rover/__init__.py
rover/cli.py
rover/main.py
reqrover-0.1.2.dist-info/METADATA
reqrover-0.1.2.dist-info/WHEEL
reqrover-0.1.2.dist-info/entry_points.txt
reqrover-0.1.2.dist-info/RECORD
