Metadata-Version: 2.4
Name: reqrover
Version: 0.1.2
Summary: A better pipreqs using only local search.
Author-email: Nicholas Ballard <nicholaesricballard@gmail.com>
Requires-Python: >=3.7
Requires-Dist: click
Requires-Dist: tomli
